{"nodes":[{"id":"4","content":"ACT[org.secuso.privacyfriendlymemory.ui.SplashActivity]1005","border":2},{"id":"9","content":"DIALOG[android.app.AlertDialog]2531, alloc: <org.secuso.privacyfriendlymemory.ui.MainActivity$WelcomeDialog: android.app.Dialog onCreateDialog(android.os.Bundle)>","border":2},{"id":"3","content":"ACT[org.secuso.privacyfriendlymemory.ui.navigation.DeckChoiceActivity]998","border":2},{"id":"10","content":"DIALOG[org.secuso.privacyfriendlymemory.ui.MemoActivity$SinglePlayerWinDialog]2214, alloc: <org.secuso.privacyfriendlymemory.ui.MemoActivity: void showWinDialog()>","border":2},{"id":"12","content":"OptionsMenu[org.secuso.privacyfriendlymemory.ui.navigation.HighscoreActivity]983","border":2},{"id":"5","content":"ACT[org.secuso.privacyfriendlymemory.ui.navigation.StatisticsActivity]1014","border":2},{"id":"2","content":"ACT[org.secuso.privacyfriendlymemory.ui.navigation.HighscoreActivity]990","border":2},{"id":"1","content":"ACT[org.secuso.privacyfriendlymemory.ui.navigation.HelpActivity]965","border":2},{"id":"7","content":"ACT[org.secuso.privacyfriendlymemory.ui.MemoActivity]1024","border":2},{"id":"6","content":"ACT[org.secuso.privacyfriendlymemory.ui.MainActivity]1019","border":2},{"id":"13","content":"OptionsMenu[org.secuso.privacyfriendlymemory.ui.navigation.StatisticsActivity]1008","border":2},{"id":"8","content":"ACT[org.secuso.privacyfriendlymemory.ui.navigation.AboutActivity]1032","border":2},{"id":"11","content":"DIALOG[org.secuso.privacyfriendlymemory.ui.MemoActivity$DuoPlayerWinDialog]2189, alloc: <org.secuso.privacyfriendlymemory.ui.MemoActivity: void showWinDialog()>","border":2},{"id":"14","content":"LAUNCHER_NODE[]2756","border":2}],"edges":[{"source":"11","target":"11","content":"implicit_power_event","id":"b8ab4c7a-93a0-4824-9d56-5b6123ed3ae9"},{"source":"4","target":"4","content":"implicit_home_event","id":"cc850a53-163a-41bc-9a47-6653297fde2a"},{"source":"3","target":"3","content":"implicit_home_event","id":"9db59426-8115-4071-990c-202c14feddb7"},{"source":"8","target":"8","content":"implicit_rotate_event","id":"feec423c-afb1-4b34-8d1f-c2ab6e9206d7"},{"source":"4","target":"14","content":"implicit_back_event","id":"285d931f-b7c0-49c0-8bf4-ca2006e67f39"},{"source":"7","target":"7","content":"implicit_home_event","id":"d90db7f0-f609-4cab-ae14-c3d83e0a6d60"},{"source":"5","target":"13","content":"click","id":"8a4712ce-d29a-4f0d-83d9-5cd0f474fa43"},{"source":"7","target":"10","content":"item_click","id":"b6c6b963-6f8a-4afe-add1-e1cf0759e0d6"},{"source":"11","target":"7","content":"implicit_rotate_event","id":"3528c824-9d89-4e5c-b009-b23886979072"},{"source":"11","target":"11","content":"implicit_home_event","id":"0d01edb5-b69c-4fd9-b600-2838eb8c9983"},{"source":"12","target":"2","content":"implicit_back_event","id":"300a9726-7f88-4832-854c-8d7f89773c4f"},{"source":"4","target":"4","content":"implicit_power_event","id":"5c3a243a-a0e2-4795-b2ee-a7f117628c35"},{"source":"5","target":"5","content":"implicit_rotate_event","id":"ab42da65-4e74-45e6-bb8b-edb5e9f17a37"},{"source":"10","target":"10","content":"implicit_power_event","id":"99d26e88-78de-46aa-bbbe-50681beaa5ed"},{"source":"1","target":"1","content":"implicit_power_event","id":"cd37b316-e7f5-48ca-91a5-de848792544b"},{"source":"13","target":"5","content":"implicit_home_event","id":"e2462573-1c7c-436a-8b85-2a14aeb2af95"},{"source":"8","target":"8","content":"implicit_home_event","id":"201abef1-eb6b-466c-9dad-703227e90609"},{"source":"6","target":"7","content":"click","id":"1030f437-42f2-42fe-943a-c1b74dc805c3"},{"source":"6","target":"7","content":"click","id":"1b1b3486-9572-4a5b-bc4b-334373750abf"},{"source":"6","target":"7","content":"click","id":"14c52b58-b950-46b1-b7f3-61ee8ae618de"},{"source":"7","target":"7","content":"implicit_rotate_event","id":"bd5353bc-c4af-43f3-99c4-52c7f8dcbe1c"},{"source":"13","target":"5","content":"click","id":"eca5953c-51c5-45e5-98c7-5f76e8273411"},{"source":"6","target":"6","content":"implicit_home_event","id":"d4a27cb8-3e4b-46d8-a183-89f95f468246"},{"source":"12","target":"2","content":"implicit_power_event","id":"e00dfb10-389c-4e1c-9cfc-3da667e8aada"},{"source":"12","target":"12","content":"implicit_rotate_event","id":"6a3df8b8-a85d-4a01-99a4-2d20e2ba15dd"},{"source":"14","target":"6","content":"implicit_launch_event","id":"4834cf24-8227-4950-aa04-a82978e09299"},{"source":"7","target":"11","content":"item_click","id":"67de3f0b-a4d1-4c61-a0fe-87821178e270"},{"source":"5","target":"5","content":"implicit_home_event","id":"bfafce35-53c0-472a-95c2-1b9722e74f9a"},{"source":"2","target":"2","content":"implicit_home_event","id":"22e06cb8-6a49-44fd-8ed1-75f0ff2908e9"},{"source":"10","target":"7","content":"implicit_rotate_event","id":"4963bb2e-42da-49d2-8c7b-aad839215f40"},{"source":"13","target":"13","content":"implicit_rotate_event","id":"4cb2bb1c-14fb-4c69-9d32-211f3854c0d7"},{"source":"10","target":"7","content":"implicit_back_event","id":"a815f150-5b86-4d95-9ec1-93c2bd588159"},{"source":"2","target":"2","content":"implicit_power_event","id":"b7de9022-886b-464d-a11a-b3f0c5cddaf6"},{"source":"2","target":"12","content":"click","id":"08f182c7-be6d-4249-bf48-cfc3f6256699"},{"source":"3","target":"3","content":"implicit_rotate_event","id":"5b120d29-978f-4a59-83d5-09bf91a05a9a"},{"source":"6","target":"6","content":"implicit_rotate_event","id":"f7eb7f22-0c2a-45ea-b3a3-221269a06846"},{"source":"4","target":"4","content":"implicit_rotate_event","id":"3d7f2b78-1c21-425a-ab4f-4ce48b8abfa6"},{"source":"1","target":"1","content":"implicit_rotate_event","id":"4b20850b-bc01-46f0-bde1-e2418ee81143"},{"source":"2","target":"2","content":"implicit_rotate_event","id":"5006236b-9baa-44f0-a335-409475be3f65"},{"source":"3","target":"3","content":"implicit_power_event","id":"0988abc2-6bb1-415e-9ca6-9065870f7e9c"},{"source":"5","target":"5","content":"implicit_power_event","id":"75f668e8-e571-4474-bfa7-6b65615509f3"},{"source":"13","target":"5","content":"implicit_back_event","id":"87535a0e-c8da-48d5-97a6-704506031251"},{"source":"7","target":"7","content":"implicit_power_event","id":"9d3a2292-4801-4ca7-9ba3-168c0d635148"},{"source":"6","target":"6","content":"click","id":"36e94d52-decd-4dd5-8b34-e2a8799d022e"},{"source":"6","target":"6","content":"click","id":"67058ed5-eb99-4f9a-acb6-1aa93929b32c"},{"source":"11","target":"7","content":"implicit_back_event","id":"ad737e32-0925-40cc-8f9c-b4e20cfc24ba"},{"source":"6","target":"6","content":"click","id":"76c4ec1b-c839-4c70-ba4b-90384db56f05"},{"source":"1","target":"1","content":"implicit_home_event","id":"3227d816-5af5-4090-bb4c-eacbf7096811"},{"source":"7","target":"7","content":"item_click","id":"b268f6bf-a278-4767-a711-e479f6fc119e"},{"source":"10","target":"10","content":"implicit_home_event","id":"7f6683c7-89ee-42d3-adeb-8ba66ba0d17f"},{"source":"13","target":"5","content":"implicit_power_event","id":"d94d2afe-41dc-4d15-9e87-1ca6107d702f"},{"source":"6","target":"4","content":"implicit_back_event","id":"ecb90c17-a7aa-41cb-a75e-97fbdc343da5"},{"source":"8","target":"8","content":"implicit_power_event","id":"4006ed6c-b5d8-4d84-946f-27682160765e"},{"source":"7","target":"6","content":"implicit_back_event","id":"ffa68923-2c35-40b0-9653-43f94653f299"},{"source":"12","target":"2","content":"click","id":"d65d22d0-be8a-4fcb-a4cb-d078acbfbf73"},{"source":"6","target":"6","content":"implicit_power_event","id":"aae62799-16fd-4a40-b178-97b78ec46b40"},{"source":"12","target":"2","content":"implicit_home_event","id":"c14b5a18-f8c5-4536-a350-5b0f9ca12143"}]}